ntcir10_math_converter/__init__.py
ntcir10_math_converter/__main__.py
ntcir10_math_converter/converter.py
ntcir10_math_converter-0.2.2.dist-info/LICENSE.txt
ntcir10_math_converter-0.2.2.dist-info/METADATA
ntcir10_math_converter-0.2.2.dist-info/RECORD
ntcir10_math_converter-0.2.2.dist-info/WHEEL
ntcir10_math_converter-0.2.2.dist-info/entry_points.txt
ntcir10_math_converter-0.2.2.dist-info/top_level.txt
