Metadata-Version: 2.1
Name: ntcir10-math-converter
Version: 0.2.2
Summary: 
Home-page: https://github.com/MIR-MU/ntcir10-math-converter
Author: Vit Novotny
Maintainer: Vit Novotny
License: MIT
Project-URL: Source, https://github.com/MIR-MU/ntcir10-math-converter
Keywords: ntcir math_information_retrieval
Platform: UNKNOWN
Classifier: Development Status :: 4 - Beta
Classifier: Environment :: Console
Classifier: Intended Audience :: Science/Research
Classifier: License :: OSI Approved :: MIT License
Classifier: Operating System :: OS Independent
Classifier: Programming Language :: Python :: 3.4
Classifier: Topic :: Scientific/Engineering :: Mathematics
Classifier: Topic :: Text Processing :: Markup :: XML
Requires-Python: ~= 3.4
Requires-Dist: beautifulsoup4 (~=4.6.0)
Requires-Dist: lxml (~=4.2.1)
Requires-Dist: tqdm (~=4.23.3)
